gdbai.py
gdbai-0.1.2.dist-info/LICENSE
gdbai-0.1.2.dist-info/METADATA
gdbai-0.1.2.dist-info/WHEEL
gdbai-0.1.2.dist-info/RECORD
