Metadata-Version: 2.1
Name: gdbai
Version: 0.1.2
Summary: gdb AI assistant
Home-page: https://github.com/airob0t/gdbai
License: GPLv3
Author: airobot
Author-email: airobot@airobot.link
Requires-Python: >=3.7.1,<4.0.0
Classifier: License :: Other/Proprietary License
Classifier: Programming Language :: Python :: 3
Classifier: Programming Language :: Python :: 3.8
Classifier: Programming Language :: Python :: 3.9
Classifier: Programming Language :: Python :: 3.10
Classifier: Programming Language :: Python :: 3.11
Requires-Dist: openai (>=0.27.8,<0.28.0)
Project-URL: Repository, https://github.com/airob0t/gdbai
